README.md
setup.py
Binomial_distributions.egg-info/PKG-INFO
Binomial_distributions.egg-info/SOURCES.txt
Binomial_distributions.egg-info/dependency_links.txt
Binomial_distributions.egg-info/not-zip-safe
Binomial_distributions.egg-info/top_level.txt
distributions/Binomialdistribution.py
distributions/Gaussiandistribution.py
distributions/Generaldistribution.py
distributions/__init__.py