Metadata-Version: 1.0
Name: Binomial-distributions
Version: 0.10.5
Summary: Gaussian distributions
Home-page: UNKNOWN
Author: UNKNOWN
Author-email: UNKNOWN
License: UNKNOWN
Platform: UNKNOWN
